assertifiers/__init__.py
assertifiers/base.py
assertifiers/container.py
assertifiers/control.py
assertifiers/equality.py
assertifiers/identity.py
assertifiers/regex.py
tests/__init__.py
tests/base.py
tests/conftest.py
assertify-3.0.dist-info/LICENSE
assertify-3.0.dist-info/METADATA
assertify-3.0.dist-info/WHEEL
assertify-3.0.dist-info/top_level.txt
assertify-3.0.dist-info/RECORD
